pyJianYingDraft/__init__.py
pyJianYingDraft/animation.py
pyJianYingDraft/audio_segment.py
pyJianYingDraft/draft_content_template.json
pyJianYingDraft/draft_folder.py
pyJianYingDraft/effect_segment.py
pyJianYingDraft/exceptions.py
pyJianYingDraft/jianying_controller.py
pyJianYingDraft/keyframe.py
pyJianYingDraft/local_materials.py
pyJianYingDraft/script_file.py
pyJianYingDraft/segment.py
pyJianYingDraft/template_mode.py
pyJianYingDraft/text_segment.py
pyJianYingDraft/time_util.py
pyJianYingDraft/track.py
pyJianYingDraft/util.py
pyJianYingDraft/video_segment.py
pyJianYingDraft/assets/__init__.py
pyJianYingDraft/assets/draft_content_template.json
pyJianYingDraft/assets/draft_meta_info.json
pyJianYingDraft/metadata/__init__.py
pyJianYingDraft/metadata/animation_meta.py
pyJianYingDraft/metadata/audio_effect_meta.py
pyJianYingDraft/metadata/audio_scene_effect.py
pyJianYingDraft/metadata/effect_meta.py
pyJianYingDraft/metadata/filter_meta.py
pyJianYingDraft/metadata/font_meta.py
pyJianYingDraft/metadata/mask_meta.py
pyJianYingDraft/metadata/speech_to_song.py
pyJianYingDraft/metadata/text_intro.py
pyJianYingDraft/metadata/text_loop.py
pyJianYingDraft/metadata/text_outro.py
pyJianYingDraft/metadata/tone_effect.py
pyJianYingDraft/metadata/transition_meta.py
pyJianYingDraft/metadata/video_character_effect.py
pyJianYingDraft/metadata/video_effect_meta.py
pyJianYingDraft/metadata/video_group_animation.py
pyJianYingDraft/metadata/video_intro.py
pyJianYingDraft/metadata/video_outro.py
pyJianYingDraft/metadata/video_scene_effect.py
tools/__init__.py
tools/build_release.py
tools/code_generator.py
tools/extract_all.py
tools/extractor_base.py
tools/jianying_extractor.py
pyJianYingDraft-0.2.5.dist-info/METADATA
pyJianYingDraft-0.2.5.dist-info/WHEEL
pyJianYingDraft-0.2.5.dist-info/top_level.txt
pyJianYingDraft-0.2.5.dist-info/RECORD
