Metadata-Version: 2.2
Name: pyJianYingDraft
Version: 0.2.5
Summary: 轻量、灵活、易上手的Python剪映草稿生成及导出工具，构建全自动化视频剪辑/混剪流水线
Home-page: https://github.com/GuanYixuan/pyJianYingDraft
Author: gary318
Classifier: Programming Language :: Python :: 3
Classifier: Development Status :: 4 - Beta
Classifier: Topic :: Multimedia :: Video
Requires-Python: >=3.8
Requires-Dist: pymediainfo
Requires-Dist: imageio
Requires-Dist: uiautomation>=2; sys_platform == "win32"
Dynamic: author
Dynamic: classifier
Dynamic: description
Dynamic: description-content-type
Dynamic: home-page
Dynamic: requires-dist
Dynamic: requires-python
Dynamic: summary
